{
  "minecraft:recipes/tools/fishing_rod": {
    "criteria": {
      "has_string": "2025-04-28 18:09:16 +0000"
    },
    "done": true
  },
  "minecraft:recipes/food/cooked_mutton_from_campfire_cooking": {
    "criteria": {
      "has_mutton": "2025-04-28 01:19:27 +0000"
    },
    "done": true
  },
  "spartanshields:recipes/spartanshields/stone_tower_shield": {
    "criteria": {
      "has_cobblestone": "2025-04-28 17:40:41 +0000"
    },
    "done": true
  },
  "minecraft:recipes/decorations/smoker": {
    "criteria": {
      "has_furnace": "2025-04-28 18:30:44 +0000"
    },
    "done": true
  },
  "minecraft:recipes/building_blocks/quartz_pillar": {
    "criteria": {
      "has_chiseled_quartz_block": "2025-04-28 18:11:15 +0000"
    },
    "done": true
  },
  "minecraft:recipes/redstone/lever": {
    "criteria": {
      "has_cobblestone": "2025-04-28 17:40:41 +0000"
    },
    "done": true
  },
  "repurposed_structures:igloos": {
    "criteria": {
      "in_igloo_grassy": "2025-04-28 17:42:47 +0000"
    },
    "done": false
  },
  "infernalexp:recipes/redstone/smooth_glowstone_button": {
    "criteria": {
      "has_smooth_glowstone": "2025-04-28 01:09:29 +0000"
    },
    "done": true
  },
  "minecraft:recipes/building_blocks/cobblestone_stairs_from_cobblestone_stonecutting": {
    "criteria": {
      "has_cobblestone": "2025-04-28 17:40:41 +0000"
    },
    "done": true
  },
  "minecraft:recipes/combat/iron_sword": {
    "criteria": {
      "has_iron_ingot": "2025-04-28 01:12:44 +0000"
    },
    "done": true
  },
  "infernalexp:recipes/food/cooked_hogchop_campfire": {
    "criteria": {
      "has_hogchop": "2025-04-28 01:09:29 +0000"
    },
    "done": true
  },
  "naturescompass:natures_compass": {
    "criteria": {
      "has_compass": "2025-04-28 01:09:29 +0000"
    },
    "done": true
  },
  "minecraft:recipes/misc/wheat": {
    "criteria": {
      "has_hay_block": "2025-04-28 01:10:58 +0000"
    },
    "done": true
  },
  "minecraft:recipes/building_blocks/polished_deepslate": {
    "criteria": {
      "has_cobbled_deepslate": "2025-04-28 17:46:00 +0000"
    },
    "done": true
  },
  "minecraft:recipes/building_blocks/chiseled_deepslate_from_cobbled_deepslate_stonecutting": {
    "criteria": {
      "has_cobbled_deepslate": "2025-04-28 17:46:00 +0000"
    },
    "done": true
  },
  "minecraft:recipes/building_blocks/red_nether_brick_slab_from_red_nether_bricks_stonecutting": {
    "criteria": {
      "has_red_nether_bricks": "2025-04-28 19:04:04 +0000"
    },
    "done": true
  },
  "minecraft:recipes/building_blocks/polished_andesite_stairs_from_andesite_stonecutting": {
    "criteria": {
      "has_andesite": "2025-04-28 17:43:35 +0000"
    },
    "done": true
  },
  "minecraft:recipes/building_blocks/chiseled_stone_bricks": {
    "criteria": {
      "has_tag": "2025-04-28 17:50:00 +0000"
    },
    "done": true
  },
  "minecraft:recipes/building_blocks/nether_brick_slab": {
    "criteria": {
      "has_nether_bricks": "2025-04-28 19:26:41 +0000"
    },
    "done": true
  },
  "minecraft:recipes/tools/iron_pickaxe": {
    "criteria": {
      "has_iron_ingot": "2025-04-28 01:12:44 +0000"
    },
    "done": true
  },
  "minecraft:recipes/building_blocks/stone_brick_slab_from_stone_bricks_stonecutting": {
    "criteria": {
      "has_stone_bricks": "2025-04-28 17:50:00 +0000"
    },
    "done": true
  },
  "minecraft:nether/root": {
    "criteria": {
      "entered_nether": "2025-04-28 17:56:59 +0000"
    },
    "done": true
  },
  "minecraft:recipes/combat/leather_helmet": {
    "criteria": {
      "has_leather": "2025-04-28 01:18:14 +0000"
    },
    "done": true
  },
  "spartanshields:recipes/spartanshields/golden_basic_shield": {
    "criteria": {
      "has_gold_ingot": "2025-04-28 01:12:45 +0000"
    },
    "done": true
  },
  "minecraft:recipes/redstone/birch_pressure_plate": {
    "criteria": {
      "has_planks": "2025-04-28 18:43:42 +0000"
    },
    "done": true
  },
  "minecraft:recipes/decorations/crafting_table": {
    "criteria": {
      "has_planks": "2025-04-28 01:17:25 +0000"
    },
    "done": true
  },
  "minecraft:recipes/decorations/campfire": {
    "criteria": {
      "has_stick": "2025-04-28 01:17:28 +0000"
    },
    "done": true
  },
  "minecraft:recipes/decorations/candle": {
    "criteria": {
      "has_string": "2025-04-28 18:09:16 +0000"
    },
    "done": true
  },
  "minecraft:recipes/tools/golden_hoe": {
    "criteria": {
      "has_gold_ingot": "2025-04-28 01:12:45 +0000"
    },
    "done": true
  },
  "incendium:misc/soul_searcher": {
    "criteria": {
      "incendium:infernal_dunes": "2025-04-28 19:34:07 +0000",
      "incendium:inverted_forest": "2025-04-28 18:47:33 +0000"
    },
    "done": false
  },
  "minecraft:recipes/food/bread": {
    "criteria": {
      "has_wheat": "2025-04-28 01:19:31 +0000"
    },
    "done": true
  },
  "packedup:recipes/packedup/basic_from_chest": {
    "criteria": {
      "recipe_condition": "2025-04-28 18:03:35 +0000"
    },
    "done": true
  },
  "minecraft:recipes/decorations/ladder": {
    "criteria": {
      "has_stick": "2025-04-28 01:17:28 +0000"
    },
    "done": true
  },
  "minecraft:recipes/misc/lapis_lazuli_from_blasting_deepslate_lapis_ore": {
    "criteria": {
      "has_deepslate_lapis_ore": "2025-04-28 17:48:06 +0000"
    },
    "done": true
  },
  "infernalexp:recipes/food/blindsight_tounge_stew": {
    "criteria": {
      "has_tongue": "2025-04-28 01:09:29 +0000",
      "has_crimson_fungus": "2025-04-28 01:09:29 +0000",
      "has_warped_fungus": "2025-04-28 01:09:29 +0000",
      "has_bowl": "2025-04-28 01:09:29 +0000",
      "has_luminous_fungus": "2025-04-28 01:09:29 +0000"
    },
    "done": true
  },
  "minecraft:recipes/misc/iron_nugget": {
    "criteria": {
      "has_iron_ingot": "2025-04-28 01:12:44 +0000"
    },
    "done": true
  },
  "minecraft:recipes/decorations/red_nether_brick_wall": {
    "criteria": {
      "has_red_nether_bricks": "2025-04-28 19:04:04 +0000"
    },
    "done": true
  },
  "minecraft:recipes/decorations/chest": {
    "criteria": {
      "has_lots_of_items": "2025-04-28 01:12:44 +0000"
    },
    "done": true
  },
  "minecraft:recipes/combat/golden_sword": {
    "criteria": {
      "has_gold_ingot": "2025-04-28 01:12:45 +0000"
    },
    "done": true
  },
  "spartanshields:recipes/spartanshields/lapis_lazuli_basic_shield": {
    "criteria": {
      "has_lapis_lazuli": "2025-04-28 17:48:11 +0000"
    },
    "done": true
  },
  "minecraft:recipes/decorations/nether_brick_wall": {
    "criteria": {
      "has_nether_bricks": "2025-04-28 19:26:41 +0000"
    },
    "done": true
  },
  "minecraft:recipes/building_blocks/cobbled_deepslate_slab": {
    "criteria": {
      "has_cobbled_deepslate": "2025-04-28 17:46:00 +0000"
    },
    "done": true
  },
  "minecraft:recipes/transportation/mangrove_boat": {
    "criteria": {
      "in_water": "2025-04-28 01:15:48 +0000"
    },
    "done": true
  },
  "minecraft:recipes/tools/wooden_shovel": {
    "criteria": {
      "has_stick": "2025-04-28 01:17:28 +0000"
    },
    "done": true
  },
  "ironchest:recipes/ironchest/chests/vanilla_dirt_chest": {
    "criteria": {
      "has_iron_ingot": "2025-04-28 01:18:48 +0000"
    },
    "done": true
  },
  "minecraft:recipes/building_blocks/deepslate_tile_slab_from_cobbled_deepslate_stonecutting": {
    "criteria": {
      "has_cobbled_deepslate": "2025-04-28 17:46:00 +0000"
    },
    "done": true
  },
  "minecraft:recipes/decorations/torch": {
    "criteria": {
      "has_stone_pickaxe": "2025-04-28 17:40:50 +0000"
    },
    "done": true
  },
  "minecraft:recipes/combat/diamond_sword": {
    "criteria": {
      "has_diamond": "2025-04-28 01:12:44 +0000"
    },
    "done": true
  },
  "midnight_madness:face_the_fear": {
    "criteria": {
      "face_the_fear": "2025-04-28 18:42:41 +0000"
    },
    "done": true
  },
  "crystalcraft_unlimited_java:iron_stick_advancement": {
    "criteria": {
      "iron_stick_advancement_0": "2025-04-28 19:02:49 +0000"
    },
    "done": true
  },
  "explorerscompass:explorers_compass_cobweb": {
    "criteria": {
      "has_recipe": "2025-04-28 01:09:29 +0000",
      "has_cobweb": "2025-04-28 01:09:29 +0000"
    },
    "done": true
  },
  "minecraft:recipes/tools/shears": {
    "criteria": {
      "has_iron_ingot": "2025-04-28 01:12:44 +0000"
    },
    "done": true
  },
  "minecraft:recipes/misc/white_dye": {
    "criteria": {
      "has_bone_meal": "2025-04-28 17:46:19 +0000"
    },
    "done": true
  },
  "infernalexp:recipes/combat/blindsight_tongue_whip": {
    "criteria": {
      "has_molten_gold_cluster": "2025-04-28 01:09:29 +0000"
    },
    "done": true
  },
  "minecraft:recipes/misc/stick": {
    "criteria": {
      "has_planks": "2025-04-28 01:17:25 +0000"
    },
    "done": true
  },
  "minecraft:recipes/decorations/jukebox": {
    "criteria": {
      "has_diamond": "2025-04-28 01:12:44 +0000"
    },
    "done": true
  },
  "minecraft:recipes/transportation/spruce_boat": {
    "criteria": {
      "in_water": "2025-04-28 01:15:48 +0000"
    },
    "done": true
  },
  "minecraft:recipes/building_blocks/cracked_stone_bricks": {
    "criteria": {
      "has_stone_bricks": "2025-04-28 17:50:00 +0000"
    },
    "done": true
  },
  "incendium:misc/root": {
    "criteria": {
      "incendium:inverted_forest": "2025-04-28 18:47:33 +0000"
    },
    "done": true
  },
  "infernalexp:recipes/food/cooked_hogchop_smelting": {
    "criteria": {
      "has_hogchop": "2025-04-28 01:09:29 +0000"
    },
    "done": true
  },
  "justhammers:recipes/justhammers.justhammers_tab/iron_hammer": {
    "criteria": {
      "has_material": "2025-04-28 01:12:44 +0000"
    },
    "done": true
  },
  "minecraft:recipes/tools/flint_and_steel": {
    "criteria": {
      "has_obsidian": "2025-04-28 17:47:55 +0000"
    },
    "done": true
  },
  "crystalcraft_unlimited_java:recipe_unlock": {
    "criteria": {
      "recipe_unlock_0": "2025-04-28 01:09:29 +0000"
    },
    "done": true
  },
  "minecraft:recipes/building_blocks/smooth_quartz_slab_from_smooth_quartz_stonecutting": {
    "criteria": {
      "has_smooth_quartz": "2025-04-28 18:12:21 +0000"
    },
    "done": true
  },
  "minecraft:recipes/building_blocks/emerald_block": {
    "criteria": {
      "has_emerald": "2025-04-28 01:13:06 +0000"
    },
    "done": true
  },
  "minecraft:recipes/misc/gold_nugget": {
    "criteria": {
      "has_gold_ingot": "2025-04-28 01:12:45 +0000"
    },
    "done": true
  },
  "minecraft:recipes/combat/iron_leggings": {
    "criteria": {
      "has_iron_ingot": "2025-04-28 01:12:44 +0000"
    },
    "done": true
  },
  "minecraft:husbandry/balanced_diet": {
    "criteria": {
      "bread": "2025-04-28 01:19:20 +0000"
    },
    "done": false
  },
  "minecraft:recipes/tools/wooden_hoe": {
    "criteria": {
      "has_stick": "2025-04-28 01:17:28 +0000"
    },
    "done": true
  },
  "minecraft:recipes/brewing/golden_carrot": {
    "criteria": {
      "has_gold_nugget": "2025-04-28 18:47:12 +0000"
    },
    "done": true
  },
  "minecraft:recipes/combat/shield": {
    "criteria": {
      "has_iron_ingot": "2025-04-28 01:12:44 +0000"
    },
    "done": true
  },
  "minecraft:recipes/building_blocks/cobblestone_slab": {
    "criteria": {
      "has_cobblestone": "2025-04-28 17:40:41 +0000"
    },
    "done": true
  },
  "minecraft:recipes/misc/bucket": {
    "criteria": {
      "has_iron_ingot": "2025-04-28 01:12:44 +0000"
    },
    "done": true
  },
  "minecraft:recipes/building_blocks/red_nether_brick_slab": {
    "criteria": {
      "has_red_nether_bricks": "2025-04-28 19:04:04 +0000"
    },
    "done": true
  },
  "minecraft:recipes/building_blocks/cobblestone_stairs": {
    "criteria": {
      "has_cobblestone": "2025-04-28 17:40:41 +0000"
    },
    "done": true
  },
  "minecraft:recipes/redstone/hopper": {
    "criteria": {
      "has_iron_ingot": "2025-04-28 01:12:44 +0000"
    },
    "done": true
  },
  "minecraft:recipes/building_blocks/stone_brick_stairs_from_stone_bricks_stonecutting": {
    "criteria": {
      "has_stone_bricks": "2025-04-28 17:50:00 +0000"
    },
    "done": true
  },
  "minecraft:recipes/building_blocks/birch_slab": {
    "criteria": {
      "has_planks": "2025-04-28 18:43:42 +0000"
    },
    "done": true
  },
  "ironchest:recipes/ironchest/chests/diamond_obsidian_chest": {
    "criteria": {
      "has_obsidian": "2025-04-28 17:47:55 +0000"
    },
    "done": true
  },
  "minecraft:recipes/decorations/cobbled_deepslate_wall_from_cobbled_deepslate_stonecutting": {
    "criteria": {
      "has_cobbled_deepslate": "2025-04-28 17:46:00 +0000"
    },
    "done": true
  },
  "incendium:infernal_dunes/root": {
    "criteria": {
      "incendium:infernal_dunes": "2025-04-28 19:34:07 +0000"
    },
    "done": true
  },
  "minecraft:recipes/transportation/jungle_chest_boat": {
    "criteria": {
      "has_boat": "2025-04-28 18:42:22 +0000"
    },
    "done": true
  },
  "minecraft:recipes/redstone/note_block": {
    "criteria": {
      "has_redstone": "2025-04-28 18:55:55 +0000"
    },
    "done": true
  },
  "naturescompass:natures_compass_sapling": {
    "criteria": {
      "has_recipe": "2025-04-28 01:09:29 +0000"
    },
    "done": true
  },
  "advancednetherite:recipes/advancednetherite.tab/netherite_emerald_ingot": {
    "criteria": {
      "has_TagKey[minecraft:item / forge:gems/emerald]": "2025-04-28 01:13:06 +0000"
    },
    "done": true
  },
  "minecraft:recipes/building_blocks/deepslate_tile_stairs_from_cobbled_deepslate_stonecutting": {
    "criteria": {
      "has_cobbled_deepslate": "2025-04-28 17:46:00 +0000"
    },
    "done": true
  },
  "minecraft:recipes/building_blocks/deepslate_tiles_from_cobbled_deepslate_stonecutting": {
    "criteria": {
      "has_cobbled_deepslate": "2025-04-28 17:46:00 +0000"
    },
    "done": true
  },
  "incendium:technical/using/shield": {
    "criteria": {
      "log_spam_fixer": "2025-04-28 01:09:30 +0000"
    },
    "done": false
  },
  "minecraft:recipes/misc/leather_horse_armor": {
    "criteria": {
      "has_leather": "2025-04-28 01:18:14 +0000"
    },
    "done": true
  },
  "minecraft:recipes/building_blocks/hay_block": {
    "criteria": {
      "has_wheat": "2025-04-28 01:19:31 +0000"
    },
    "done": true
  },
  "minecraft:recipes/misc/lapis_lazuli_from_smelting_deepslate_lapis_ore": {
    "criteria": {
      "has_deepslate_lapis_ore": "2025-04-28 17:48:06 +0000"
    },
    "done": true
  },
  "minecraft:recipes/combat/leather_leggings": {
    "criteria": {
      "has_leather": "2025-04-28 01:18:14 +0000"
    },
    "done": true
  },
  "minecraft:recipes/combat/iron_helmet": {
    "criteria": {
      "has_iron_ingot": "2025-04-28 01:12:44 +0000"
    },
    "done": true
  },
  "minecraft:recipes/tools/golden_shovel": {
    "criteria": {
      "has_gold_ingot": "2025-04-28 01:12:45 +0000"
    },
    "done": true
  },
  "minecraft:recipes/combat/bow": {
    "criteria": {
      "has_string": "2025-04-28 18:09:16 +0000"
    },
    "done": true
  },
  "minecraft:recipes/redstone/oak_fence_gate": {
    "criteria": {
      "has_planks": "2025-04-28 01:17:25 +0000"
    },
    "done": true
  },
  "incendium:technical/using/trailblazer": {
    "criteria": {
      "log_spam_fixer": "2025-04-28 01:09:30 +0000"
    },
    "done": false
  },
  "spartanshields:recipes/spartanshields/stone_basic_shield": {
    "criteria": {
      "has_cobblestone": "2025-04-28 17:40:41 +0000"
    },
    "done": true
  },
  "minecraft:recipes/decorations/iron_bars": {
    "criteria": {
      "has_iron_ingot": "2025-04-28 01:12:44 +0000"
    },
    "done": true
  },
  "spartanshields:recipes/spartanshields/golden_tower_shield": {
    "criteria": {
      "has_gold_ingot": "2025-04-28 01:12:45 +0000"
    },
    "done": true
  },
  "minecraft:recipes/building_blocks/andesite_stairs_from_andesite_stonecutting": {
    "criteria": {
      "has_andesite": "2025-04-28 17:43:35 +0000"
    },
    "done": true
  },
  "incendium:technical/scroll_of_returning": {
    "criteria": {
      "log_spam_fixer": "2025-04-28 01:09:30 +0000"
    },
    "done": false
  },
  "minecraft:recipes/building_blocks/gold_block": {
    "criteria": {
      "has_gold_ingot": "2025-04-28 01:12:45 +0000"
    },
    "done": true
  },
  "minecraft:recipes/transportation/acacia_chest_boat": {
    "criteria": {
      "has_boat": "2025-04-28 18:42:22 +0000"
    },
    "done": true
  },
  "minecraft:story/obtain_armor": {
    "criteria": {
      "iron_boots": "2025-04-28 18:11:08 +0000"
    },
    "done": true
  },
  "minecraft:recipes/combat/diamond_chestplate": {
    "criteria": {
      "has_diamond": "2025-04-28 01:12:44 +0000"
    },
    "done": true
  },
  "minecraft:recipes/transportation/oak_chest_boat": {
    "criteria": {
      "has_boat": "2025-04-28 18:42:22 +0000"
    },
    "done": true
  },
  "minecraft:story/mine_stone": {
    "criteria": {
      "get_stone": "2025-04-28 17:40:41 +0000"
    },
    "done": true
  },
  "minecraft:recipes/redstone/target": {
    "criteria": {
      "has_hay_block": "2025-04-28 01:10:58 +0000"
    },
    "done": true
  },
  "minecraft:recipes/transportation/minecart": {
    "criteria": {
      "has_iron_ingot": "2025-04-28 01:12:44 +0000"
    },
    "done": true
  },
  "minecraft:recipes/decorations/furnace": {
    "criteria": {
      "has_cobblestone": "2025-04-28 17:40:41 +0000"
    },
    "done": true
  },
  "advancednetherite:recipes/advancednetherite.tab/netherite_iron_ingot": {
    "criteria": {
      "has_TagKey[minecraft:item / forge:ingots/iron]": "2025-04-28 01:12:44 +0000"
    },
    "done": true
  },
  "minecraft:recipes/decorations/deepslate_brick_wall_from_cobbled_deepslate_stonecutting": {
    "criteria": {
      "has_cobbled_deepslate": "2025-04-28 17:46:00 +0000"
    },
    "done": true
  },
  "minecraft:recipes/brewing/cauldron": {
    "criteria": {
      "has_water_bucket": "2025-04-28 18:29:12 +0000"
    },
    "done": true
  },
  "minecraft:recipes/combat/diamond_leggings": {
    "criteria": {
      "has_diamond": "2025-04-28 01:12:44 +0000"
    },
    "done": true
  },
  "minecraft:recipes/misc/charcoal": {
    "criteria": {
      "has_log": "2025-04-28 01:15:57 +0000"
    },
    "done": true
  },
  "minecraft:adventure/sleep_in_bed": {
    "criteria": {
      "slept_in_bed": "2025-04-28 17:40:05 +0000"
    },
    "done": true
  },
  "minecraft:recipes/building_blocks/andesite_stairs": {
    "criteria": {
      "has_andesite": "2025-04-28 17:43:35 +0000"
    },
    "done": true
  },
  "infernalexp:recipes/food/cured_jerky": {
    "criteria": {
      "has_soul_salt_clump": "2025-04-28 01:09:29 +0000"
    },
    "done": true
  },
  "minecraft:recipes/tools/iron_hoe": {
    "criteria": {
      "has_iron_ingot": "2025-04-28 01:12:44 +0000"
    },
    "done": true
  },
  "minecraft:recipes/tools/wooden_pickaxe": {
    "criteria": {
      "has_stick": "2025-04-28 01:17:28 +0000"
    },
    "done": true
  },
  "minecraft:recipes/building_blocks/cobblestone_slab_from_cobblestone_stonecutting": {
    "criteria": {
      "has_cobblestone": "2025-04-28 17:40:41 +0000"
    },
    "done": true
  },
  "minecraft:recipes/building_blocks/cobbled_deepslate_stairs": {
    "criteria": {
      "has_cobbled_deepslate": "2025-04-28 17:46:00 +0000"
    },
    "done": true
  },
  "minecraft:husbandry/root": {
    "criteria": {
      "consumed_item": "2025-04-28 01:19:20 +0000"
    },
    "done": true
  },
  "minecraft:recipes/building_blocks/stone_brick_slab": {
    "criteria": {
      "has_stone_bricks": "2025-04-28 17:50:00 +0000"
    },
    "done": true
  },
  "minecraft:recipes/redstone/redstone_torch": {
    "criteria": {
      "has_redstone": "2025-04-28 18:55:55 +0000"
    },
    "done": true
  },
  "infernalexp:recipes/redstone/basalt_button": {
    "criteria": {
      "has_basalt": "2025-04-28 01:09:29 +0000"
    },
    "done": true
  },
  "minecraft:recipes/transportation/birch_boat": {
    "criteria": {
      "in_water": "2025-04-28 01:15:48 +0000"
    },
    "done": true
  },
  "minecraft:recipes/food/golden_apple": {
    "criteria": {
      "has_gold_ingot": "2025-04-28 01:12:45 +0000"
    },
    "done": true
  },
  "minecraft:recipes/building_blocks/oak_stairs": {
    "criteria": {
      "has_planks": "2025-04-28 01:17:25 +0000"
    },
    "done": true
  },
  "minecraft:recipes/building_blocks/quartz_stairs": {
    "criteria": {
      "has_chiseled_quartz_block": "2025-04-28 18:11:15 +0000"
    },
    "done": true
  },
  "minecraft:recipes/building_blocks/polished_andesite_slab_from_andesite_stonecutting": {
    "criteria": {
      "has_andesite": "2025-04-28 17:43:35 +0000"
    },
    "done": true
  },
  "ironchest:recipes/ironchest/chests/copper_iron_chest": {
    "criteria": {
      "has_item": "2025-04-28 01:12:44 +0000"
    },
    "done": true
  },
  "minecraft:recipes/decorations/enchanting_table": {
    "criteria": {
      "has_obsidian": "2025-04-28 17:47:55 +0000"
    },
    "done": true
  },
  "minecraft:recipes/building_blocks/polished_andesite_from_andesite_stonecutting": {
    "criteria": {
      "has_andesite": "2025-04-28 17:43:35 +0000"
    },
    "done": true
  },
  "minecraft:recipes/building_blocks/cobbled_deepslate_stairs_from_cobbled_deepslate_stonecutting": {
    "criteria": {
      "has_cobbled_deepslate": "2025-04-28 17:46:00 +0000"
    },
    "done": true
  },
  "minecraft:recipes/tools/iron_shovel": {
    "criteria": {
      "has_iron_ingot": "2025-04-28 01:12:44 +0000"
    },
    "done": true
  },
  "minecraft:recipes/transportation/acacia_boat": {
    "criteria": {
      "in_water": "2025-04-28 01:15:48 +0000"
    },
    "done": true
  },
  "minecraft:recipes/redstone/iron_trapdoor": {
    "criteria": {
      "has_iron_ingot": "2025-04-28 01:12:44 +0000"
    },
    "done": true
  },
  "packedup:basic_backpack": {
    "criteria": {
      "has_backpack": "2025-04-28 18:25:13 +0000"
    },
    "done": true
  },
  "minecraft:recipes/decorations/birch_sign": {
    "criteria": {
      "has_planks": "2025-04-28 18:43:42 +0000"
    },
    "done": true
  },
  "minecraft:recipes/building_blocks/smooth_quartz_slab": {
    "criteria": {
      "has_smooth_quartz": "2025-04-28 18:12:21 +0000"
    },
    "done": true
  },
  "spartanshields:recipes/spartanshields/diamond_tower_shield": {
    "criteria": {
      "has_diamond": "2025-04-28 01:12:44 +0000"
    },
    "done": true
  },
  "minecraft:adventure/root": {
    "criteria": {
      "killed_something": "2025-04-28 01:18:08 +0000"
    },
    "done": true
  },
  "minecraft:recipes/transportation/dark_oak_chest_boat": {
    "criteria": {
      "has_boat": "2025-04-28 18:42:22 +0000"
    },
    "done": true
  },
  "infernalexp:recipes/redstone/soul_slate_button": {
    "criteria": {
      "has_soul_slate": "2025-04-28 01:09:29 +0000"
    },
    "done": true
  },
  "justhammers:recipes/justhammers.justhammers_tab/gold_hammer": {
    "criteria": {
      "has_material": "2025-04-28 01:12:45 +0000"
    },
    "done": true
  },
  "minecraft:recipes/decorations/item_frame": {
    "criteria": {
      "has_leather": "2025-04-28 01:18:14 +0000"
    },
    "done": true
  },
  "minecraft:recipes/tools/stone_hoe": {
    "criteria": {
      "has_cobblestone": "2025-04-28 17:40:41 +0000"
    },
    "done": true
  },
  "minecraft:recipes/building_blocks/white_wool_from_string": {
    "criteria": {
      "has_string": "2025-04-28 18:09:16 +0000"
    },
    "done": true
  },
  "minecraft:recipes/tools/clock": {
    "criteria": {
      "has_redstone": "2025-04-28 18:55:55 +0000"
    },
    "done": true
  },
  "minecraft:recipes/tools/diamond_pickaxe": {
    "criteria": {
      "has_diamond": "2025-04-28 01:12:44 +0000"
    },
    "done": true
  },
  "minecraft:recipes/tools/diamond_hoe": {
    "criteria": {
      "has_diamond": "2025-04-28 01:12:44 +0000"
    },
    "done": true
  },
  "minecraft:recipes/food/baked_potato_from_smoking": {
    "criteria": {
      "has_potato": "2025-04-28 01:13:06 +0000"
    },
    "done": true
  },
  "minecraft:recipes/tools/diamond_shovel": {
    "criteria": {
      "has_diamond": "2025-04-28 01:12:44 +0000"
    },
    "done": true
  },
  "minecraft:adventure/kill_all_mobs": {
    "criteria": {
      "minecraft:blaze": "2025-04-28 19:41:28 +0000",
      "minecraft:skeleton": "2025-04-28 17:44:03 +0000",
      "minecraft:zombified_piglin": "2025-04-28 19:07:30 +0000",
      "minecraft:wither_skeleton": "2025-04-28 19:16:46 +0000",
      "minecraft:piglin": "2025-04-28 19:10:15 +0000",
      "minecraft:zombie": "2025-04-28 17:53:42 +0000"
    },
    "done": false
  },
  "minecraft:story/enter_the_nether": {
    "criteria": {
      "entered_nether": "2025-04-28 17:56:59 +0000"
    },
    "done": true
  },
  "minecraft:recipes/building_blocks/birch_wood": {
    "criteria": {
      "has_log": "2025-04-28 18:43:38 +0000"
    },
    "done": true
  },
  "minecraft:recipes/building_blocks/polished_deepslate_from_cobbled_deepslate_stonecutting": {
    "criteria": {
      "has_cobbled_deepslate": "2025-04-28 17:46:00 +0000"
    },
    "done": true
  },
  "minecraft:recipes/redstone/redstone_block": {
    "criteria": {
      "has_redstone": "2025-04-28 18:55:55 +0000"
    },
    "done": true
  },
  "minecraft:recipes/building_blocks/deepslate": {
    "criteria": {
      "has_cobbled_deepslate": "2025-04-28 17:46:00 +0000"
    },
    "done": true
  },
  "minecraft:recipes/food/baked_potato": {
    "criteria": {
      "has_potato": "2025-04-28 01:13:06 +0000"
    },
    "done": true
  },
  "minecraft:recipes/food/cooked_beef_from_smoking": {
    "criteria": {
      "has_beef": "2025-04-28 01:18:12 +0000"
    },
    "done": true
  },
  "minecraft:recipes/decorations/stone_brick_wall": {
    "criteria": {
      "has_stone_bricks": "2025-04-28 17:50:00 +0000"
    },
    "done": true
  },
  "minecraft:recipes/decorations/fletching_table": {
    "criteria": {
      "has_flint": "2025-04-28 17:50:50 +0000"
    },
    "done": true
  },
  "minecraft:recipes/misc/iron_nugget_from_smelting": {
    "criteria": {
      "has_iron_sword": "2025-04-28 17:41:33 +0000"
    },
    "done": true
  },
  "minecraft:recipes/food/cooked_mutton_from_smoking": {
    "criteria": {
      "has_mutton": "2025-04-28 01:19:27 +0000"
    },
    "done": true
  },
  "minecraft:recipes/building_blocks/polished_deepslate_slab_from_cobbled_deepslate_stonecutting": {
    "criteria": {
      "has_cobbled_deepslate": "2025-04-28 17:46:00 +0000"
    },
    "done": true
  },
  "minecraft:recipes/building_blocks/cracked_nether_bricks": {
    "criteria": {
      "has_nether_bricks": "2025-04-28 19:26:41 +0000"
    },
    "done": true
  },
  "minecraft:recipes/redstone/birch_door": {
    "criteria": {
      "has_planks": "2025-04-28 18:43:42 +0000"
    },
    "done": true
  },
  "spartanshields:recipes/spartanshields/iron_tower_shield": {
    "criteria": {
      "has_iron_ingot": "2025-04-28 01:12:44 +0000"
    },
    "done": true
  },
  "minecraft:recipes/transportation/birch_chest_boat": {
    "criteria": {
      "has_boat": "2025-04-28 18:42:22 +0000"
    },
    "done": true
  },
  "naturescompass:natures_compass_log": {
    "criteria": {
      "has_recipe": "2025-04-28 01:09:29 +0000"
    },
    "done": true
  },
  "spartanshields:recipes/spartanshields/iron_basic_shield": {
    "criteria": {
      "has_iron_ingot": "2025-04-28 01:12:44 +0000"
    },
    "done": true
  },
  "minecraft:recipes/decorations/chain": {
    "criteria": {
      "has_iron_ingot": "2025-04-28 01:12:44 +0000"
    },
    "done": true
  },
  "minecraft:recipes/misc/gold_ingot_from_nuggets": {
    "criteria": {
      "has_gold_nugget": "2025-04-28 18:47:12 +0000"
    },
    "done": true
  },
  "minecraft:story/mine_diamond": {
    "criteria": {
      "diamond": "2025-04-28 01:12:44 +0000"
    },
    "done": true
  },
  "minecraft:story/upgrade_tools": {
    "criteria": {
      "stone_pickaxe": "2025-04-28 17:40:50 +0000"
    },
    "done": true
  },
  "minecraft:recipes/decorations/nether_brick_wall_from_nether_bricks_stonecutting": {
    "criteria": {
      "has_nether_bricks": "2025-04-28 19:26:41 +0000"
    },
    "done": true
  },
  "minecraft:recipes/combat/diamond_helmet": {
    "criteria": {
      "has_diamond": "2025-04-28 01:12:44 +0000"
    },
    "done": true
  },
  "minecraft:recipes/misc/blue_dye": {
    "criteria": {
      "has_lapis_lazuli": "2025-04-28 17:48:11 +0000"
    },
    "done": true
  },
  "minecraft:recipes/decorations/oak_fence": {
    "criteria": {
      "has_planks": "2025-04-28 01:17:25 +0000"
    },
    "done": true
  },
  "minecraft:recipes/transportation/oak_boat": {
    "criteria": {
      "in_water": "2025-04-28 01:15:48 +0000"
    },
    "done": true
  },
  "advancednetherite:recipes/advancednetherite.tab/netherite_gold_ingot": {
    "criteria": {
      "has_TagKey[minecraft:item / forge:ingots/gold]": "2025-04-28 01:12:45 +0000"
    },
    "done": true
  },
  "alexsmobs:alexsmobs/crimson_mosquito": {
    "criteria": {
      "killed_by": "2025-04-28 19:31:40 +0000"
    },
    "done": true
  },
  "infernalexp:recipes/redstone/soul_slate_pressure_plate": {
    "criteria": {
      "has_soul_slate": "2025-04-28 01:09:29 +0000"
    },
    "done": true
  },
  "minecraft:recipes/decorations/birch_fence": {
    "criteria": {
      "has_planks": "2025-04-28 18:43:42 +0000"
    },
    "done": true
  },
  "minecraft:recipes/food/baked_potato_from_campfire_cooking": {
    "criteria": {
      "has_potato": "2025-04-28 01:13:06 +0000"
    },
    "done": true
  },
  "minecraft:recipes/food/cooked_porkchop": {
    "criteria": {
      "has_porkchop": "2025-04-28 01:19:29 +0000"
    },
    "done": true
  },
  "minecraft:recipes/building_blocks/oak_slab": {
    "criteria": {
      "has_planks": "2025-04-28 01:17:25 +0000"
    },
    "done": true
  },
  "minecraft:recipes/building_blocks/stone_brick_stairs": {
    "criteria": {
      "has_stone_bricks": "2025-04-28 17:50:00 +0000"
    },
    "done": true
  },
  "minecraft:recipes/combat/golden_boots": {
    "criteria": {
      "has_gold_ingot": "2025-04-28 01:12:45 +0000"
    },
    "done": true
  },
  "minecraft:recipes/food/cooked_porkchop_from_campfire_cooking": {
    "criteria": {
      "has_porkchop": "2025-04-28 01:19:29 +0000"
    },
    "done": true
  },
  "minecraft:recipes/tools/wooden_axe": {
    "criteria": {
      "has_stick": "2025-04-28 01:17:28 +0000"
    },
    "done": true
  },
  "minecraft:recipes/brewing/blaze_powder": {
    "criteria": {
      "has_blaze_rod": "2025-04-28 19:41:31 +0000"
    },
    "done": true
  },
  "dungeons_arise:find_small_blimp": {
    "criteria": {
      "location0": "2025-04-28 18:06:03 +0000"
    },
    "done": true
  },
  "minecraft:recipes/building_blocks/chiseled_nether_bricks_from_nether_bricks_stonecutting": {
    "criteria": {
      "has_nether_bricks": "2025-04-28 19:26:41 +0000"
    },
    "done": true
  },
  "minecraft:recipes/combat/golden_chestplate": {
    "criteria": {
      "has_gold_ingot": "2025-04-28 01:12:45 +0000"
    },
    "done": true
  },
  "minecraft:recipes/decorations/deepslate_tile_wall_from_cobbled_deepslate_stonecutting": {
    "criteria": {
      "has_cobbled_deepslate": "2025-04-28 17:46:00 +0000"
    },
    "done": true
  },
  "minecraft:recipes/decorations/loom": {
    "criteria": {
      "has_string": "2025-04-28 18:09:16 +0000"
    },
    "done": true
  },
  "minecraft:recipes/misc/iron_ingot_from_blasting_raw_iron": {
    "criteria": {
      "has_raw_iron": "2025-04-28 17:44:07 +0000"
    },
    "done": true
  },
  "minecraft:recipes/tools/diamond_axe": {
    "criteria": {
      "has_diamond": "2025-04-28 01:12:44 +0000"
    },
    "done": true
  },
  "minecraft:recipes/decorations/stone_brick_wall_from_stone_bricks_stonecutting": {
    "criteria": {
      "has_stone_bricks": "2025-04-28 17:50:00 +0000"
    },
    "done": true
  },
  "minecraft:recipes/building_blocks/red_nether_brick_stairs": {
    "criteria": {
      "has_red_nether_bricks": "2025-04-28 19:04:04 +0000"
    },
    "done": true
  },
  "spartanshields:recipes/spartanshields/wooden_tower_shield": {
    "criteria": {
      "has_planks": "2025-04-28 01:17:25 +0000"
    },
    "done": true
  },
  "minecraft:nether/find_fortress": {
    "criteria": {
      "fortress": "2025-04-28 19:17:54 +0000"
    },
    "done": true
  },
  "minecraft:recipes/building_blocks/chiseled_stone_bricks_from_stone_bricks_stonecutting": {
    "criteria": {
      "has_stone_bricks": "2025-04-28 17:50:00 +0000"
    },
    "done": true
  },
  "packedup:recipes/packedup/copper_from_basic": {
    "criteria": {
      "recipe_condition": "2025-04-28 18:25:13 +0000"
    },
    "done": true
  },
  "minecraft:recipes/building_blocks/nether_brick_stairs_from_nether_bricks_stonecutting": {
    "criteria": {
      "has_nether_bricks": "2025-04-28 19:26:41 +0000"
    },
    "done": true
  },
  "minecraft:recipes/building_blocks/iron_block": {
    "criteria": {
      "has_iron_ingot": "2025-04-28 01:12:44 +0000"
    },
    "done": true
  },
  "minecraft:recipes/redstone/birch_button": {
    "criteria": {
      "has_planks": "2025-04-28 18:43:42 +0000"
    },
    "done": true
  },
  "minecraft:recipes/building_blocks/quartz_slab": {
    "criteria": {
      "has_chiseled_quartz_block": "2025-04-28 18:11:15 +0000"
    },
    "done": true
  },
  "minecraft:recipes/misc/red_dye_from_poppy": {
    "criteria": {
      "has_poppy": "2025-04-28 01:18:10 +0000"
    },
    "done": true
  },
  "minecraft:recipes/misc/nether_brick": {
    "criteria": {
      "has_netherrack": "2025-04-28 18:43:38 +0000"
    },
    "done": true
  },
  "ironchest:recipes/ironchest/chests/iron_gold_chest": {
    "criteria": {
      "has_gold_ingot": "2025-04-28 01:12:45 +0000"
    },
    "done": true
  },
  "minecraft:recipes/building_blocks/andesite_slab_from_andesite_stonecutting": {
    "criteria": {
      "has_andesite": "2025-04-28 17:43:35 +0000"
    },
    "done": true
  },
  "minecraft:recipes/combat/arrow": {
    "criteria": {
      "has_flint": "2025-04-28 17:50:50 +0000"
    },
    "done": true
  },
  "minecraft:recipes/building_blocks/coal_block": {
    "criteria": {
      "has_coal": "2025-04-28 01:19:28 +0000"
    },
    "done": true
  },
  "packedup:recipes/packedup/iron_from_basic": {
    "criteria": {
      "recipe_condition": "2025-04-28 18:25:13 +0000"
    },
    "done": true
  },
  "minecraft:recipes/decorations/red_nether_brick_wall_from_red_nether_bricks_stonecutting": {
    "criteria": {
      "has_red_nether_bricks": "2025-04-28 19:04:04 +0000"
    },
    "done": true
  },
  "minecraft:recipes/redstone/light_weighted_pressure_plate": {
    "criteria": {
      "has_gold_ingot": "2025-04-28 01:12:45 +0000"
    },
    "done": true
  },
  "minecraft:story/deflect_arrow": {
    "criteria": {
      "deflected_projectile": "2025-04-28 17:44:02 +0000"
    },
    "done": true
  },
  "minecraft:recipes/misc/gold_nugget_from_blasting": {
    "criteria": {
      "has_golden_pickaxe": "2025-04-28 17:46:17 +0000"
    },
    "done": true
  },
  "minecraft:recipes/combat/wooden_sword": {
    "criteria": {
      "has_stick": "2025-04-28 01:17:28 +0000"
    },
    "done": true
  },
  "minecraft:recipes/tools/stone_shovel": {
    "criteria": {
      "has_cobblestone": "2025-04-28 17:40:41 +0000"
    },
    "done": true
  },
  "minecraft:recipes/building_blocks/oak_planks": {
    "criteria": {
      "has_logs": "2025-04-28 01:15:57 +0000"
    },
    "done": true
  },
  "spartanshields:recipes/spartanshields/diamond_basic_shield": {
    "criteria": {
      "has_diamond": "2025-04-28 01:12:44 +0000"
    },
    "done": true
  },
  "crystalcraft_unlimited_java:is_this_a_joke_to_you": {
    "criteria": {
      "is_this_a_joke_to_you_0": "2025-04-28 19:42:49 +0000"
    },
    "done": true
  },
  "minecraft:recipes/tools/golden_axe": {
    "criteria": {
      "has_gold_ingot": "2025-04-28 01:12:45 +0000"
    },
    "done": true
  },
  "spartanshields:recipes/spartanshields/obsidian_tower_shield": {
    "criteria": {
      "has_obsidian": "2025-04-28 17:47:55 +0000"
    },
    "done": true
  },
  "minecraft:recipes/tools/iron_axe": {
    "criteria": {
      "has_iron_ingot": "2025-04-28 01:12:44 +0000"
    },
    "done": true
  },
  "minecraft:recipes/transportation/mangrove_chest_boat": {
    "criteria": {
      "has_boat": "2025-04-28 18:42:22 +0000"
    },
    "done": true
  },
  "minecraft:recipes/combat/golden_helmet": {
    "criteria": {
      "has_gold_ingot": "2025-04-28 01:12:45 +0000"
    },
    "done": true
  },
  "minecraft:recipes/redstone/tripwire_hook": {
    "criteria": {
      "has_string": "2025-04-28 18:09:16 +0000"
    },
    "done": true
  },
  "minecraft:recipes/redstone/oak_pressure_plate": {
    "criteria": {
      "has_planks": "2025-04-28 01:17:25 +0000"
    },
    "done": true
  },
  "minecraft:recipes/combat/iron_boots": {
    "criteria": {
      "has_iron_ingot": "2025-04-28 01:12:44 +0000"
    },
    "done": true
  },
  "minecraft:recipes/misc/bone_meal": {
    "criteria": {
      "has_bone": "2025-04-28 17:44:03 +0000"
    },
    "done": true
  },
  "spartanshields:recipes/spartanshields/obsidian_basic_shield": {
    "criteria": {
      "has_obsidian": "2025-04-28 17:47:55 +0000"
    },
    "done": true
  },
  "minecraft:recipes/building_blocks/chiseled_quartz_block": {
    "criteria": {
      "has_chiseled_quartz_block": "2025-04-28 18:11:15 +0000"
    },
    "done": true
  },
  "minecraft:recipes/building_blocks/birch_planks": {
    "criteria": {
      "has_logs": "2025-04-28 18:43:38 +0000"
    },
    "done": true
  },
  "minecraft:recipes/building_blocks/polished_deepslate_stairs_from_cobbled_deepslate_stonecutting": {
    "criteria": {
      "has_cobbled_deepslate": "2025-04-28 17:46:00 +0000"
    },
    "done": true
  },
  "infernalexp:recipes/redstone/smooth_glowstone_pressure_plate": {
    "criteria": {
      "has_smooth_glowstone": "2025-04-28 01:09:29 +0000"
    },
    "done": true
  },
  "ironchest:recipes/ironchest/chests/gold_diamond_chest": {
    "criteria": {
      "has_diamonds": "2025-04-28 01:12:44 +0000"
    },
    "done": true
  },
  "packedup:recipes/packedup/silver_from_iron": {
    "criteria": {
      "recipe_condition": "2025-04-28 18:34:07 +0000"
    },
    "done": true
  },
  "minecraft:recipes/building_blocks/oak_wood": {
    "criteria": {
      "has_log": "2025-04-28 01:15:57 +0000"
    },
    "done": true
  },
  "minecraft:recipes/redstone/birch_fence_gate": {
    "criteria": {
      "has_planks": "2025-04-28 18:43:42 +0000"
    },
    "done": true
  },
  "minecraft:story/root": {
    "criteria": {
      "crafting_table": "2025-04-28 01:12:34 +0000"
    },
    "done": true
  },
  "minecraft:recipes/building_blocks/smooth_quartz_stairs": {
    "criteria": {
      "has_smooth_quartz": "2025-04-28 18:12:21 +0000"
    },
    "done": true
  },
  "minecraft:recipes/combat/iron_chestplate": {
    "criteria": {
      "has_iron_ingot": "2025-04-28 01:12:44 +0000"
    },
    "done": true
  },
  "minecraft:recipes/combat/crossbow": {
    "criteria": {
      "has_iron_ingot": "2025-04-28 01:12:44 +0000"
    },
    "done": true
  },
  "minecraft:recipes/redstone/dropper": {
    "criteria": {
      "has_redstone": "2025-04-28 18:55:55 +0000"
    },
    "done": true
  },
  "minecraft:recipes/decorations/cobbled_deepslate_wall": {
    "criteria": {
      "has_cobbled_deepslate": "2025-04-28 17:46:00 +0000"
    },
    "done": true
  },
  "minecraft:recipes/misc/coal": {
    "criteria": {
      "has_coal_block": "2025-04-28 18:27:32 +0000"
    },
    "done": true
  },
  "minecraft:recipes/transportation/spruce_chest_boat": {
    "criteria": {
      "has_boat": "2025-04-28 18:42:22 +0000"
    },
    "done": true
  },
  "minecraft:recipes/decorations/oak_sign": {
    "criteria": {
      "has_planks": "2025-04-28 01:17:25 +0000"
    },
    "done": true
  },
  "minecraft:recipes/food/cooked_porkchop_from_smoking": {
    "criteria": {
      "has_porkchop": "2025-04-28 01:19:29 +0000"
    },
    "done": true
  },
  "minecraft:recipes/redstone/oak_trapdoor": {
    "criteria": {
      "has_planks": "2025-04-28 01:17:25 +0000"
    },
    "done": true
  },
  "minecraft:story/form_obsidian": {
    "criteria": {
      "obsidian": "2025-04-28 17:47:55 +0000"
    },
    "done": true
  },
  "minecraft:recipes/brewing/brewing_stand": {
    "criteria": {
      "has_blaze_rod": "2025-04-28 19:41:31 +0000"
    },
    "done": true
  },
  "minecraft:recipes/building_blocks/nether_brick_slab_from_nether_bricks_stonecutting": {
    "criteria": {
      "has_nether_bricks": "2025-04-28 19:26:41 +0000"
    },
    "done": true
  },
  "minecraft:recipes/misc/iron_nugget_from_blasting": {
    "criteria": {
      "has_iron_sword": "2025-04-28 17:41:33 +0000"
    },
    "done": true
  },
  "minecraft:recipes/decorations/polished_deepslate_wall_from_cobbled_deepslate_stonecutting": {
    "criteria": {
      "has_cobbled_deepslate": "2025-04-28 17:46:00 +0000"
    },
    "done": true
  },
  "ironchest:recipes/ironchest/upgrades/iron_to_gold_chest_upgrade": {
    "criteria": {
      "has_iron_ingot": "2025-04-28 01:12:44 +0000"
    },
    "done": true
  },
  "minecraft:recipes/combat/leather_chestplate": {
    "criteria": {
      "has_leather": "2025-04-28 01:18:14 +0000"
    },
    "done": true
  },
  "explorerscompass:explorers_compass_cracked_stone_bricks": {
    "criteria": {
      "has_cracked_stone_bricks": "2025-04-28 01:09:29 +0000"
    },
    "done": true
  },
  "minecraft:recipes/tools/compass": {
    "criteria": {
      "has_redstone": "2025-04-28 18:55:55 +0000"
    },
    "done": true
  },
  "minecraft:adventure/kill_a_mob": {
    "criteria": {
      "minecraft:skeleton": "2025-04-28 17:44:03 +0000"
    },
    "done": true
  },
  "infernalexp:recipes/building_blocks/glass": {
    "criteria": {
      "has_silt": "2025-04-28 01:09:29 +0000"
    },
    "done": true
  },
  "infernalexp:recipes/food/cooked_hogchop_smoking": {
    "criteria": {
      "has_hogchop": "2025-04-28 01:09:29 +0000"
    },
    "done": true
  },
  "minecraft:recipes/redstone/oak_button": {
    "criteria": {
      "has_planks": "2025-04-28 01:17:25 +0000"
    },
    "done": true
  },
  "minecraft:recipes/tools/golden_pickaxe": {
    "criteria": {
      "has_gold_ingot": "2025-04-28 01:12:45 +0000"
    },
    "done": true
  },
  "infernalexp:recipes/combat/glowsilk_bow": {
    "criteria": {
      "has_glowsilk": "2025-04-28 01:09:29 +0000"
    },
    "done": true
  },
  "minecraft:nether/obtain_blaze_rod": {
    "criteria": {
      "blaze_rod": "2025-04-28 19:41:31 +0000"
    },
    "done": true
  },
  "minecraft:recipes/building_blocks/stone": {
    "criteria": {
      "has_cobblestone": "2025-04-28 17:40:41 +0000"
    },
    "done": true
  },
  "minecraft:recipes/building_blocks/polished_andesite": {
    "criteria": {
      "has_andesite": "2025-04-28 17:43:35 +0000"
    },
    "done": true
  },
  "minecraft:recipes/building_blocks/deepslate_bricks_from_cobbled_deepslate_stonecutting": {
    "criteria": {
      "has_cobbled_deepslate": "2025-04-28 17:46:00 +0000"
    },
    "done": true
  },
  "minecraft:recipes/food/cooked_beef": {
    "criteria": {
      "has_beef": "2025-04-28 01:18:12 +0000"
    },
    "done": true
  },
  "minecraft:recipes/building_blocks/smooth_quartz_stairs_from_smooth_quartz_stonecutting": {
    "criteria": {
      "has_smooth_quartz": "2025-04-28 18:12:21 +0000"
    },
    "done": true
  },
  "infernalexp:recipes/redstone/smooth_dullstone_button": {
    "criteria": {
      "has_smooth_dullstone": "2025-04-28 01:09:29 +0000"
    },
    "done": true
  },
  "minecraft:adventure/adventuring_time": {
    "criteria": {
      "minecraft:river": "2025-04-28 17:55:59 +0000",
      "minecraft:meadow": "2025-04-28 17:49:32 +0000",
      "minecraft:plains": "2025-04-28 01:09:30 +0000"
    },
    "done": false
  },
  "minecraft:recipes/redstone/iron_door": {
    "criteria": {
      "has_iron_ingot": "2025-04-28 01:12:44 +0000"
    },
    "done": true
  },
  "minecraft:recipes/building_blocks/deepslate_brick_stairs_from_cobbled_deepslate_stonecutting": {
    "criteria": {
      "has_cobbled_deepslate": "2025-04-28 17:46:00 +0000"
    },
    "done": true
  },
  "midnight_madness:soul_collector": {
    "criteria": {
      "soul_collector": "2025-04-28 18:10:11 +0000"
    },
    "done": true
  },
  "ironchest:recipes/ironchest/chests/vanilla_iron_chest": {
    "criteria": {
      "has_iron_ingot": "2025-04-28 01:12:44 +0000"
    },
    "done": true
  },
  "minecraft:recipes/decorations/composter": {
    "criteria": {
      "has_wood_slab": "2025-04-28 18:28:15 +0000"
    },
    "done": true
  },
  "incendium:technical/using/ragnarok": {
    "criteria": {
      "log_spam_fixer": "2025-04-28 01:09:30 +0000"
    },
    "done": false
  },
  "spartanshields:recipes/spartanshields/wooden_basic_shield": {
    "criteria": {
      "has_planks": "2025-04-28 01:17:25 +0000"
    },
    "done": true
  },
  "repurposed_structures:outposts": {
    "criteria": {
      "in_outpost_nether_brick": "2025-04-28 18:58:12 +0000"
    },
    "done": false
  },
  "minecraft:recipes/decorations/nether_brick_fence": {
    "criteria": {
      "has_nether_bricks": "2025-04-28 19:26:41 +0000"
    },
    "done": true
  },
  "minecraft:recipes/combat/stone_sword": {
    "criteria": {
      "has_cobblestone": "2025-04-28 17:40:41 +0000"
    },
    "done": true
  },
  "minecraft:recipes/decorations/barrel": {
    "criteria": {
      "has_planks": "2025-04-28 01:17:25 +0000"
    },
    "done": true
  },
  "minecraft:recipes/decorations/cobblestone_wall": {
    "criteria": {
      "has_cobblestone": "2025-04-28 17:40:41 +0000"
    },
    "done": true
  },
  "incendium:technical/new_player": {
    "criteria": {
      "requirement": "2025-04-28 01:09:29 +0000"
    },
    "done": true
  },
  "minecraft:recipes/building_blocks/red_nether_brick_stairs_from_red_nether_bricks_stonecutting": {
    "criteria": {
      "has_red_nether_bricks": "2025-04-28 19:04:04 +0000"
    },
    "done": true
  },
  "minecraft:recipes/misc/iron_ingot_from_smelting_raw_iron": {
    "criteria": {
      "has_raw_iron": "2025-04-28 17:44:07 +0000"
    },
    "done": true
  },
  "minecraft:recipes/tools/stone_pickaxe": {
    "criteria": {
      "has_cobblestone": "2025-04-28 17:40:41 +0000"
    },
    "done": true
  },
  "minecraft:recipes/decorations/smithing_table": {
    "criteria": {
      "has_iron_ingot": "2025-04-28 01:12:44 +0000"
    },
    "done": true
  },
  "minecraft:recipes/misc/iron_ingot_from_nuggets": {
    "criteria": {
      "has_iron_nugget": "2025-04-28 18:38:08 +0000"
    },
    "done": true
  },
  "minecraft:recipes/redstone/oak_door": {
    "criteria": {
      "has_planks": "2025-04-28 01:17:25 +0000"
    },
    "done": true
  },
  "minecraft:recipes/building_blocks/deepslate_brick_slab_from_cobbled_deepslate_stonecutting": {
    "criteria": {
      "has_cobbled_deepslate": "2025-04-28 17:46:00 +0000"
    },
    "done": true
  },
  "explorerscompass:explorers_compass": {
    "criteria": {
      "has_recipe": "2025-04-28 01:09:29 +0000",
      "has_compass": "2025-04-28 01:09:29 +0000"
    },
    "done": true
  },
  "minecraft:recipes/combat/leather_boots": {
    "criteria": {
      "has_leather": "2025-04-28 01:18:14 +0000"
    },
    "done": true
  },
  "minecraft:recipes/transportation/jungle_boat": {
    "criteria": {
      "in_water": "2025-04-28 01:15:48 +0000"
    },
    "done": true
  },
  "minecraft:recipes/decorations/cobblestone_wall_from_cobblestone_stonecutting": {
    "criteria": {
      "has_cobblestone": "2025-04-28 17:40:41 +0000"
    },
    "done": true
  },
  "infernalexp:recipes/redstone/smooth_dimstone_button": {
    "criteria": {
      "has_smooth_dimstone": "2025-04-28 01:09:29 +0000"
    },
    "done": true
  },
  "minecraft:recipes/building_blocks/birch_stairs": {
    "criteria": {
      "has_planks": "2025-04-28 18:43:42 +0000"
    },
    "done": true
  },
  "ironchest:recipes/ironchest/upgrades/wood_to_iron_chest_upgrade": {
    "criteria": {
      "has_iron_ingot": "2025-04-28 01:12:44 +0000"
    },
    "done": true
  },
  "minecraft:recipes/building_blocks/diamond_block": {
    "criteria": {
      "has_diamond": "2025-04-28 01:12:44 +0000"
    },
    "done": true
  },
  "minecraft:recipes/redstone/heavy_weighted_pressure_plate": {
    "criteria": {
      "has_iron_ingot": "2025-04-28 01:12:44 +0000"
    },
    "done": true
  },
  "minecraft:recipes/transportation/dark_oak_boat": {
    "criteria": {
      "in_water": "2025-04-28 01:15:48 +0000"
    },
    "done": true
  },
  "minecraft:recipes/decorations/andesite_wall_from_andesite_stonecutting": {
    "criteria": {
      "has_andesite": "2025-04-28 17:43:35 +0000"
    },
    "done": true
  },
  "packedup:recipes/packedup/gold_from_iron": {
    "criteria": {
      "recipe_condition": "2025-04-28 18:34:07 +0000"
    },
    "done": true
  },
  "minecraft:recipes/building_blocks/lapis_block": {
    "criteria": {
      "has_lapis_lazuli": "2025-04-28 17:48:11 +0000"
    },
    "done": true
  },
  "minecraft:recipes/building_blocks/nether_brick_stairs": {
    "criteria": {
      "has_nether_bricks": "2025-04-28 19:26:41 +0000"
    },
    "done": true
  },
  "dungeons_arise:wda_root": {
    "criteria": {
      "WDA": "2025-04-28 01:09:29 +0000"
    },
    "done": true
  },
  "packedup:iron_or_copper_backpack": {
    "criteria": {
      "has_iron_backpack": "2025-04-28 18:34:07 +0000"
    },
    "done": true
  },
  "justhammers:recipes/justhammers.justhammers_tab/diamond_hammer": {
    "criteria": {
      "has_material": "2025-04-28 01:12:44 +0000"
    },
    "done": true
  },
  "minecraft:recipes/redstone/birch_trapdoor": {
    "criteria": {
      "has_planks": "2025-04-28 18:43:42 +0000"
    },
    "done": true
  },
  "minecraft:recipes/combat/golden_leggings": {
    "criteria": {
      "has_gold_ingot": "2025-04-28 01:12:45 +0000"
    },
    "done": true
  },
  "minecraft:recipes/redstone/piston": {
    "criteria": {
      "has_redstone": "2025-04-28 18:55:55 +0000"
    },
    "done": true
  },
  "minecraft:recipes/decorations/lantern": {
    "criteria": {
      "has_iron_ingot": "2025-04-28 01:12:44 +0000"
    },
    "done": true
  },
  "crystalcraft_unlimited_java:the_strongest_stick": {
    "criteria": {
      "the_strongest_stick_0": "2025-04-28 19:14:53 +0000"
    },
    "done": true
  },
  "infernalexp:recipes/redstone/polished_basalt_pressure_plate": {
    "criteria": {
      "has_polished_basalt": "2025-04-28 01:09:29 +0000"
    },
    "done": true
  },
  "minecraft:nether/explore_nether": {
    "criteria": {
      "minecraft:nether_wastes": "2025-04-28 17:56:59 +0000",
      "minecraft:soul_sand_valley": "2025-04-28 19:39:21 +0000",
      "minecraft:warped_forest": "2025-04-28 18:48:43 +0000"
    },
    "done": false
  },
  "minecraft:recipes/food/cooked_beef_from_campfire_cooking": {
    "criteria": {
      "has_beef": "2025-04-28 01:18:12 +0000"
    },
    "done": true
  },
  "minecraft:recipes/misc/gold_nugget_from_smelting": {
    "criteria": {
      "has_golden_pickaxe": "2025-04-28 17:46:17 +0000"
    },
    "done": true
  },
  "minecraft:recipes/combat/diamond_boots": {
    "criteria": {
      "has_diamond": "2025-04-28 01:12:44 +0000"
    },
    "done": true
  },
  "advancednetherite:recipes/advancednetherite.tab/netherite_diamond_ingot": {
    "criteria": {
      "has_TagKey[minecraft:item / forge:gems/diamond]": "2025-04-28 01:12:44 +0000"
    },
    "done": true
  },
  "minecraft:recipes/building_blocks/cobbled_deepslate_slab_from_cobbled_deepslate_stonecutting": {
    "criteria": {
      "has_cobbled_deepslate": "2025-04-28 17:46:00 +0000"
    },
    "done": true
  },
  "ironchest:recipes/ironchest/upgrades/wood_to_copper_chest_upgrade": {
    "criteria": {
      "has_item": "2025-04-28 01:17:25 +0000"
    },
    "done": true
  },
  "minecraft:recipes/decorations/andesite_wall": {
    "criteria": {
      "has_andesite": "2025-04-28 17:43:35 +0000"
    },
    "done": true
  },
  "midnight_madness:midnight_madness_advancement": {
    "criteria": {
      "midnight_madness_advancement": "2025-04-28 01:09:29 +0000"
    },
    "done": true
  },
  "minecraft:recipes/building_blocks/andesite_slab": {
    "criteria": {
      "has_andesite": "2025-04-28 17:43:35 +0000"
    },
    "done": true
  },
  "incendium:root": {
    "criteria": {
      "requirement": "2025-04-28 17:56:59 +0000"
    },
    "done": true
  },
  "minecraft:recipes/decorations/soul_campfire": {
    "criteria": {
      "has_stick": "2025-04-28 01:17:28 +0000"
    },
    "done": true
  },
  "minecraft:story/smelt_iron": {
    "criteria": {
      "iron": "2025-04-28 01:12:44 +0000"
    },
    "done": true
  },
  "minecraft:recipes/tools/stone_axe": {
    "criteria": {
      "has_cobblestone": "2025-04-28 17:40:41 +0000"
    },
    "done": true
  },
  "minecraft:recipes/food/cooked_mutton": {
    "criteria": {
      "has_mutton": "2025-04-28 01:19:27 +0000"
    },
    "done": true
  },
  "minecraft:recipes/building_blocks/raw_iron_block": {
    "criteria": {
      "has_raw_iron": "2025-04-28 17:44:07 +0000"
    },
    "done": true
  },
  "repurposed_structures:root": {
    "criteria": {
      "always": "2025-04-28 01:09:29 +0000"
    },
    "done": true
  },
  "minecraft:recipes/building_blocks/bone_block": {
    "criteria": {
      "has_bone_meal": "2025-04-28 17:46:19 +0000"
    },
    "done": true
  },
  "DataVersion": 3120
}